aria2local.py
py_ztj_aria2local-0.0.1.dist-info/METADATA
py_ztj_aria2local-0.0.1.dist-info/WHEEL
py_ztj_aria2local-0.0.1.dist-info/top_level.txt
py_ztj_aria2local-0.0.1.dist-info/RECORD
